pytest_aggreport/hooks.py
pytest_aggreport/plugin.py
pytest_aggreport/resources/aggreport.css
pytest_aggreport-0.1.5.dist-info/LICENSE
pytest_aggreport-0.1.5.dist-info/METADATA
pytest_aggreport-0.1.5.dist-info/WHEEL
pytest_aggreport-0.1.5.dist-info/entry_points.txt
pytest_aggreport-0.1.5.dist-info/top_level.txt
pytest_aggreport-0.1.5.dist-info/RECORD
