Metadata-Version: 2.1
Name: pytest-aggreport
Version: 0.1.5
Summary: pytest plugin for pytest-repeat that generate aggregate report of the same test cases with additional statistics details.
Home-page: https://github.com/hdw868/pytest-aggreport
Author: Wayne Hong
Author-email: hdw868@126.com
Maintainer: Wayne Hong
Maintainer-email: hdw868@126.com
License: MIT
Platform: UNKNOWN
Classifier: Development Status :: 4 - Beta
Classifier: Framework :: Pytest
Classifier: Intended Audience :: Developers
Classifier: Topic :: Software Development :: Quality Assurance
Classifier: Topic :: Software Development :: Testing
Classifier: Topic :: Utilities
Classifier: Programming Language :: Python :: 3.6
Classifier: Programming Language :: Python :: 3.7
Classifier: Programming Language :: Python :: 3.8
Classifier: Programming Language :: Python :: Implementation :: CPython
Classifier: Programming Language :: Python :: Implementation :: PyPy
Classifier: Operating System :: OS Independent
Classifier: License :: OSI Approved :: MIT License
Requires-Python: >=3.6, !=3.0.*, !=3.1.*, !=3.2.*, !=3.3.*
Requires-Dist: pytest (>=6.2.2)
Requires-Dist: beautifultable (>=1.0.1)
Requires-Dist: py (>=1.8.0)
Requires-Dist: pytest-repeat (>=0.8.0)
